scaffoldai/__init__.py
scaffoldai/main.py
scaffold_ai-0.1.5.dist-info/METADATA
scaffold_ai-0.1.5.dist-info/WHEEL
scaffold_ai-0.1.5.dist-info/entry_points.txt
scaffold_ai-0.1.5.dist-info/top_level.txt
scaffold_ai-0.1.5.dist-info/RECORD
