Metadata-Version: 2.4
Name: scaffold-ai
Version: 0.1.5
Summary: AI-powered project scaffolding tool
Author-email: Vincent Valero <vjtvalero@gmail.com>
License: MIT
Project-URL: Homepage, https://github.com/vjtvalero/scaffold-ai
Requires-Python: >=3.8
Requires-Dist: openai>=1.84.0
